CHANGES.txt
MANIFEST.in
README.rst
setup.py
pyramid_whoauth/__init__.py
pyramid_whoauth/auth.py
pyramid_whoauth/tests.py
pyramid_whoauth/tweens.py
pyramid_whoauth/utils.py
pyramid_whoauth/views.py
pyramid_whoauth.egg-info/PKG-INFO
pyramid_whoauth.egg-info/SOURCES.txt
pyramid_whoauth.egg-info/dependency_links.txt
pyramid_whoauth.egg-info/not-zip-safe
pyramid_whoauth.egg-info/paster_plugins.txt
pyramid_whoauth.egg-info/requires.txt
pyramid_whoauth.egg-info/top_level.txt