Metadata-Version: 1.0
Name: pyramid-whoauth
Version: 0.1.2
Summary: pyramid_whoauth
Home-page: https://github.com/mozilla-services/pyramid_whoauth
Author: Mozilla Services
Author-email: services-dev@mozilla.org
License: UNKNOWN
Keywords: web pyramid pylons authentication
Platform: UNKNOWN
Classifier: Programming Language :: Python
Classifier: Framework :: Pylons
Classifier: Topic :: Internet :: WWW/HTTP
